marinholab/papers/icra2023/orbital_manipulation/__init__.py
marinholab/papers/icra2023/orbital_manipulation/_lbr4_kinematics.py
marinholab/papers/icra2023/orbital_manipulation/_main.py
marinholab/papers/icra2023/orbital_manipulation/_orbital_manipulation.py
marinholab/papers/icra2023/orbital_manipulation/_robot_manager.py
marinholab_papers_icra2023_orbitalmanipulation-25.5.12.dist-info/licenses/LICENSE
marinholab_papers_icra2023_orbitalmanipulation-25.5.12.dist-info/METADATA
marinholab_papers_icra2023_orbitalmanipulation-25.5.12.dist-info/WHEEL
marinholab_papers_icra2023_orbitalmanipulation-25.5.12.dist-info/entry_points.txt
marinholab_papers_icra2023_orbitalmanipulation-25.5.12.dist-info/top_level.txt
marinholab_papers_icra2023_orbitalmanipulation-25.5.12.dist-info/RECORD
